glassnodeapi/__init__.py
glassnodeapi/enums.py
glassnodeapi/glassnode.py
glassnodeapi/py.typed
glassnodeapi-0.1.4.dist-info/METADATA
glassnodeapi-0.1.4.dist-info/WHEEL
glassnodeapi-0.1.4.dist-info/licenses/LICENSE
glassnodeapi-0.1.4.dist-info/RECORD
