Metadata-Version: 2.4
Name: glassnodeapi
Version: 0.1.4
Author-email: narumi <toucans-cutouts0f@icloud.com>
License-File: LICENSE
Requires-Python: >=3.12
Requires-Dist: httpx>=0.28.1
Requires-Dist: iso8601>=2.1.0
Requires-Dist: pandas>=2.2.3
Requires-Dist: python-dotenv>=1.1.0
